huckleberry_api/__init__.py
huckleberry_api/api.py
huckleberry_api/const.py
huckleberry_api/py.typed
huckleberry_api/types.py
huckleberry_api-0.1.18.dist-info/WHEEL
huckleberry_api-0.1.18.dist-info/METADATA
huckleberry_api-0.1.18.dist-info/RECORD
