Metadata-Version: 2.3
Name: huckleberry-api
Version: 0.1.18
Summary: Python API client for Huckleberry baby tracking app using Firebase Firestore
Keywords: huckleberry,baby,tracking,firebase,api
Author: Woyken
Author-email: Woyken <13166802+Woyken@users.noreply.github.com>
License: MIT
Classifier: Development Status :: 4 - Beta
Classifier: Intended Audience :: Developers
Classifier: License :: OSI Approved :: MIT License
Classifier: Programming Language :: Python :: 3
Classifier: Programming Language :: Python :: 3.9
Classifier: Programming Language :: Python :: 3.10
Classifier: Programming Language :: Python :: 3.11
Classifier: Programming Language :: Python :: 3.12
Requires-Dist: google-cloud-firestore>=2.11.0
Requires-Dist: requests>=2.31.0
Requires-Dist: tzdata>=2024.1
Requires-Python: >=3.9
Project-URL: Homepage, https://github.com/Woyken/py-huckleberry-api
Project-URL: Issues, https://github.com/Woyken/py-huckleberry-api/issues
Project-URL: Repository, https://github.com/Woyken/py-huckleberry-api
